clg.py
clg/__init__.py
clg/__init__.pyi
clg/py.typed
clg-3.3.0.dist-info/LICENSE
clg-3.3.0.dist-info/METADATA
clg-3.3.0.dist-info/WHEEL
clg-3.3.0.dist-info/top_level.txt
clg-3.3.0.dist-info/RECORD
