Metadata-Version: 2.1
Name: clg
Version: 3.3.0
Summary: Command-line generator from a dictionary.
Home-page: https://clg.readthedocs.org/en/latest/
Download-URL: https://github.com/fmenabe/python-clg
Author: François Ménabé
Author-email: francois.menabe@gmail.com
License: MIT License
Keywords: command-line,argparse,wrapper,YAML,JSON
Classifier: Development Status :: 5 - Production/Stable
Classifier: Environment :: Console
Classifier: Intended Audience :: Developers
Classifier: Intended Audience :: System Administrators
Classifier: License :: OSI Approved :: MIT License
Classifier: Programming Language :: Python
Classifier: Programming Language :: Python :: 3.4
Classifier: Programming Language :: Python :: 3.5
Classifier: Programming Language :: Python :: 3.6
Classifier: Programming Language :: Python :: 3.7
Classifier: Programming Language :: Python :: 3.8
Classifier: Programming Language :: Python :: 3.9
Classifier: Programming Language :: Python :: 3.10
Classifier: Topic :: Utilities
License-File: LICENSE
